<?xml version="1.0" encoding="utf-8"?>
<odoo>
    <data>
        <template id="report_emp_leave_summary">
            <t t-call="report.html_container">
                <t t-call="report.external_layout">
                    <!--<t t-foreach="docs" t-as="o">-->
                    <div class="page" style="page-break-inside: auto">
                        <div class="row">
                            <div class="col-xs-12" style="text-align:center;">
                                <h2><strong>Employee Leave Summary Report</strong></h2>
                                <hr/>
                            </div>
                        </div>
                        <div style=" background-color:#D6EAF8; font-size:15px">
                            <div class="row">
                                <div class="col-xs-8">
                                    <div class="col-xs-8" style="text-align:left;padding-top: 10px;"><strong>Operating Unit : </strong><span t-esc="form['to_date']"/></div>
                                </div>
                                <div class="col-xs-4">
                                    <div class="row">
                                        <div class="col-xs-8"><strong>Date From : </strong><span t-esc="form['from_date']"/></div>
                                        <div class="col-xs-8"><strong>Date To : </strong><span t-esc="form['to_date']"/></div>
                                    </div>
                                </div>
                            </div>
                        </div>
                        <br/>

                        <table class="table table-bordered" style="width:100%">
                            <thead>
                                <tr style="background-color:#C0C0C0;">
                                    <th style="text-align:center;padding-bottom: 25px;" rowspan="2">SL</th>
                                    <th style="text-align:center;padding-bottom: 25px;" rowspan="2">Name</th>
                                    <th style="text-align:center;padding-bottom: 25px;" rowspan="2">Designation</th>
                                    <th style="text-align:center;padding-bottom: 25px;" rowspan="2">Department</th>
                                    <th style="text-align:center;" colspan="2">Casual Leave</th>
                                    <th style="text-align:center;" colspan="2">Sick Leave</th>
                                    <th style="text-align:center;" colspan="2">Earn Leave</th>
                                </tr>
                                <tr style="background-color:#C0C0C0;">
                                    <th style="text-align:center;">Avail</th>
                                    <th style="text-align:center;">Balance</th>
                                    <th style="text-align:center;">Avail</th>
                                    <th style="text-align:center;">Balance</th>
                                    <th style="text-align:center;">Avail</th>
                                    <th style="text-align:center;">Balance</th>
                                </tr>
                            </thead>
                            <!--<tbody>-->
                                <!--<t t-foreach="record['att_summary_list']" t-as="emp">-->
                                    <!--<tr>-->
                                        <!--<td><span t-esc="l_index+1"/></td>-->
                                        <!--<td><span t-esc="emp['emp_name']"></span></td>-->
                                        <!--<td><span t-esc="emp['dept']"></span></td>-->
                                        <!--<td><span t-esc="emp['designation']"></span></td>-->
                                        <!--<t t-foreach="dynamic_col_list" t-as="c">-->
                                            <!--<td class="text-right"><span t-esc="emp[c]"></span></td>-->
                                        <!--</t>-->
                                    <!--</tr>-->
                                <!--</t>-->
                            <!--</tbody>-->
                        </table>
                        <!--<footer>-->
                            <!--<p><b>Submitted by:</b> <span t-field="o.requested_by"/></p>-->
                            <!--<p><b>First Approval by:</b> <span t-field="o.approver1_id"/></p>-->
                            <!--<p><b>Final Approval by: </b><span t-field="o.approver2_id"/></p>-->
                        <!--</footer>-->
                    </div>
                </t>
            </t>
        </template>
        <report id="report_leave_summary"
            string="Leaves Summary"
            model="hr.holidays"
            report_type="qweb-pdf"
            name="gbs_hr_leave_report.report_emp_leave_summary"
            file="gbs_hr_leave_report.report_emp_leave_summary"
            menu="False"
        />
    </data>
</odoo>
