<?xml version="1.0" encoding="utf-8"?>
<odoo>

    <record id="module_category_loan" model="ir.module.category" >
        <field name="name">Loan</field>
        <field name="sequence">200</field>
    </record>

    <record id="group_manager_loan" model="res.groups">
        <field name="name">Loan Manager</field>
        <field name="category_id" ref="module_category_loan"/>
    </record>

    <record id="group_user_loan" model="res.groups">
        <field name="name">Loan User</field>
        <field name="category_id" ref="module_category_loan"/>
    </record>

</odoo>

